setup.cfg
setup.py
textpass/__init__.py
textpass/authentication.py
textpass/challenge.py
textpass/models.py
textpass/routes.py
textpass.egg-info/PKG-INFO
textpass.egg-info/SOURCES.txt
textpass.egg-info/dependency_links.txt
textpass.egg-info/requires.txt
textpass.egg-info/top_level.txt