Metadata-Version: 1.1
Name: textpass
Version: 0.2
Summary: Register and authenticate using only a phone number
Home-page: https://github.com/pycal/textpass
Author: Cailen McQuattie
Author-email: cailen.mac@gmail.com
License: UNKNOWN
Download-URL: https://github.com/pycal/textpass/tarball/0.2
Keywords: registration,authentication,mobile
Platform: UNKNOWN
